{
  "Font Family": {
    "SEM": {
      "font-family-serif": {
        "$type": "string",
        "$value": "Georgia",
        "$extensions": {
          "com.figma.type": "string",
          "com.figma.variableId": "VariableID:5162:472",
          "com.figma.hiddenFromPublishing": true,
          "com.figma.scopes": [
            "ALL_SCOPES"
          ]
        }
      },
      "font-family-sans-serif": {
        "$type": "string",
        "$value": "Euclid Circular B",
        "$extensions": {
          "com.figma.type": "string",
          "com.figma.variableId": "VariableID:5162:473",
          "com.figma.hiddenFromPublishing": true,
          "com.figma.scopes": [
            "ALL_SCOPES"
          ]
        }
      }
    },
    "ForbesMedia - SEO": {
      "font-family-heading-serif": {
        "$type": "string",
        "$value": "Schnyder S",
        "$extensions": {
          "com.figma.type": "string",
          "com.figma.variableId": "VariableID:5162:490",
          "com.figma.hiddenFromPublishing": true,
          "com.figma.scopes": [
            "ALL_SCOPES"
          ]
        }
      },
      "font-family-heading": {
        "$type": "string",
        "$value": "Work Sans",
        "$extensions": {
          "com.figma.type": "string",
          "com.figma.variableId": "VariableID:5162:487",
          "com.figma.hiddenFromPublishing": true,
          "com.figma.scopes": [
            "ALL_SCOPES"
          ]
        }
      },
      "font-family-body": {
        "$type": "string",
        "$value": "Georgia",
        "$extensions": {
          "com.figma.type": "string",
          "com.figma.variableId": "VariableID:5162:489",
          "com.figma.hiddenFromPublishing": true,
          "com.figma.scopes": [
            "ALL_SCOPES"
          ]
        }
      },
      "font-family-body-serif": {
        "$type": "string",
        "$value": "Work Sans",
        "$extensions": {
          "com.figma.type": "string",
          "com.figma.variableId": "VariableID:5162:488",
          "com.figma.hiddenFromPublishing": true,
          "com.figma.scopes": [
            "ALL_SCOPES"
          ]
        }
      },
      "font-family-breadcrumbs": {
        "$type": "string",
        "$value": "String value",
        "$extensions": {
          "com.figma.type": "string",
          "com.figma.variableId": "VariableID:5284:35",
          "com.figma.hiddenFromPublishing": true,
          "com.figma.scopes": [
            "ALL_SCOPES"
          ]
        }
      }
    }
  },
  "Line height": {
    "line-height-5xl": {
      "$type": "number",
      "$value": 40,
      "$extensions": {
        "com.figma.variableId": "VariableID:5162:523",
        "com.figma.hiddenFromPublishing": true,
        "com.figma.scopes": [
          "LINE_HEIGHT"
        ]
      }
    },
    "line-height-4xl": {
      "$type": "number",
      "$value": 36,
      "$extensions": {
        "com.figma.variableId": "VariableID:5162:520",
        "com.figma.hiddenFromPublishing": true,
        "com.figma.scopes": [
          "LINE_HEIGHT"
        ]
      }
    },
    "line-height-3xl": {
      "$type": "number",
      "$value": 28,
      "$extensions": {
        "com.figma.variableId": "VariableID:5162:521",
        "com.figma.hiddenFromPublishing": true,
        "com.figma.scopes": [
          "LINE_HEIGHT"
        ]
      }
    },
    "line-height-2xl": {
      "$type": "number",
      "$value": 28,
      "$extensions": {
        "com.figma.variableId": "VariableID:5162:519",
        "com.figma.hiddenFromPublishing": true,
        "com.figma.scopes": [
          "LINE_HEIGHT"
        ]
      }
    },
    "line-height-xl": {
      "$type": "number",
      "$value": 24,
      "$extensions": {
        "com.figma.variableId": "VariableID:5162:518",
        "com.figma.hiddenFromPublishing": true,
        "com.figma.scopes": [
          "LINE_HEIGHT"
        ]
      }
    },
    "line-height-lg": {
      "$type": "number",
      "$value": 22,
      "$extensions": {
        "com.figma.variableId": "VariableID:5162:517",
        "com.figma.hiddenFromPublishing": true,
        "com.figma.scopes": [
          "LINE_HEIGHT"
        ]
      }
    },
    "line-height-md": {
      "$type": "number",
      "$value": 20,
      "$extensions": {
        "com.figma.variableId": "VariableID:5162:514",
        "com.figma.hiddenFromPublishing": true,
        "com.figma.scopes": [
          "LINE_HEIGHT"
        ]
      }
    },
    "line-height-sm": {
      "$type": "number",
      "$value": 20,
      "$extensions": {
        "com.figma.variableId": "VariableID:5162:522",
        "com.figma.hiddenFromPublishing": true,
        "com.figma.scopes": [
          "LINE_HEIGHT"
        ]
      }
    },
    "line-height-xs": {
      "$type": "number",
      "$value": 18,
      "$extensions": {
        "com.figma.variableId": "VariableID:5162:516",
        "com.figma.hiddenFromPublishing": true,
        "com.figma.scopes": [
          "LINE_HEIGHT"
        ]
      }
    },
    "line-height-2xs": {
      "$type": "number",
      "$value": 16,
      "$extensions": {
        "com.figma.variableId": "VariableID:5162:515",
        "com.figma.hiddenFromPublishing": true,
        "com.figma.scopes": [
          "LINE_HEIGHT"
        ]
      }
    }
  },
  "Font weight": {
    "font-weight-bold": {
      "$type": "number",
      "$value": 700,
      "$extensions": {
        "com.figma.variableId": "VariableID:5162:545",
        "com.figma.hiddenFromPublishing": true,
        "com.figma.scopes": [
          "FONT_STYLE"
        ]
      }
    },
    "font-weight-semibold": {
      "$type": "number",
      "$value": 600,
      "$extensions": {
        "com.figma.variableId": "VariableID:5162:547",
        "com.figma.hiddenFromPublishing": true,
        "com.figma.scopes": [
          "FONT_STYLE"
        ]
      }
    },
    "font-weight-medium": {
      "$type": "number",
      "$value": 500,
      "$extensions": {
        "com.figma.variableId": "VariableID:5162:548",
        "com.figma.hiddenFromPublishing": true,
        "com.figma.scopes": [
          "FONT_STYLE"
        ]
      }
    },
    "font-weight-regular": {
      "$type": "number",
      "$value": 400,
      "$extensions": {
        "com.figma.variableId": "VariableID:5162:546",
        "com.figma.hiddenFromPublishing": true,
        "com.figma.scopes": [
          "FONT_STYLE"
        ]
      }
    },
    "font-weight-light": {
      "$type": "number",
      "$value": 300,
      "$extensions": {
        "com.figma.variableId": "VariableID:5162:549",
        "com.figma.hiddenFromPublishing": true,
        "com.figma.scopes": [
          "FONT_STYLE"
        ]
      }
    }
  },
  "Letter Spacing": {
    "spacing-tighter": {
      "$type": "number",
      "$value": -0.20000000298023224,
      "$extensions": {
        "com.figma.variableId": "VariableID:5162:570",
        "com.figma.hiddenFromPublishing": true,
        "com.figma.scopes": [
          "LETTER_SPACING"
        ]
      }
    },
    "spacing-wider": {
      "$type": "number",
      "$value": 1,
      "$extensions": {
        "com.figma.variableId": "VariableID:5162:568",
        "com.figma.hiddenFromPublishing": true,
        "com.figma.scopes": [
          "LETTER_SPACING"
        ]
      }
    },
    "spacing-tight": {
      "$type": "number",
      "$value": -0.10000000149011612,
      "$extensions": {
        "com.figma.variableId": "VariableID:5162:567",
        "com.figma.hiddenFromPublishing": true,
        "com.figma.scopes": [
          "LETTER_SPACING"
        ]
      }
    },
    "spacing-normal": {
      "$type": "number",
      "$value": 0,
      "$extensions": {
        "com.figma.variableId": "VariableID:5162:569",
        "com.figma.hiddenFromPublishing": true,
        "com.figma.scopes": [
          "LETTER_SPACING"
        ]
      }
    },
    "spacing-wide": {
      "$type": "number",
      "$value": 0.5,
      "$extensions": {
        "com.figma.variableId": "VariableID:5162:566",
        "com.figma.hiddenFromPublishing": true,
        "com.figma.scopes": [
          "LETTER_SPACING"
        ]
      }
    }
  },
  "Font Size": {
    "SEM": {
      "display": {
        "$type": "number",
        "$value": 32,
        "$extensions": {
          "com.figma.variableId": "VariableID:5162:618",
          "com.figma.scopes": [
            "FONT_SIZE"
          ]
        }
      },
      "heading-lg": {
        "$type": "number",
        "$value": 28,
        "$extensions": {
          "com.figma.variableId": "VariableID:5162:614",
          "com.figma.scopes": [
            "FONT_SIZE"
          ]
        }
      },
      "heading-md": {
        "$type": "number",
        "$value": 24,
        "$extensions": {
          "com.figma.variableId": "VariableID:5162:609",
          "com.figma.scopes": [
            "FONT_SIZE"
          ]
        }
      },
      "heading-sm": {
        "$type": "number",
        "$value": 20,
        "$extensions": {
          "com.figma.variableId": "VariableID:5162:608",
          "com.figma.scopes": [
            "FONT_SIZE"
          ]
        }
      },
      "title-lg": {
        "$type": "number",
        "$value": 18,
        "$extensions": {
          "com.figma.variableId": "VariableID:5162:607",
          "com.figma.scopes": [
            "FONT_SIZE"
          ]
        }
      },
      "title-md": {
        "$type": "number",
        "$value": 16,
        "$extensions": {
          "com.figma.variableId": "VariableID:5162:606",
          "com.figma.scopes": [
            "FONT_SIZE"
          ]
        }
      },
      "title-sm": {
        "$type": "number",
        "$value": 16,
        "$extensions": {
          "com.figma.variableId": "VariableID:5162:605",
          "com.figma.scopes": [
            "FONT_SIZE"
          ]
        }
      },
      "title-xs": {
        "$type": "number",
        "$value": 14,
        "$extensions": {
          "com.figma.variableId": "VariableID:5206:546",
          "com.figma.scopes": [
            "FONT_SIZE"
          ]
        }
      },
      "body-lg": {
        "$type": "number",
        "$value": 16,
        "$extensions": {
          "com.figma.variableId": "VariableID:5162:610",
          "com.figma.scopes": [
            "FONT_SIZE"
          ]
        }
      },
      "body-md": {
        "$type": "number",
        "$value": 16,
        "$extensions": {
          "com.figma.variableId": "VariableID:5162:613",
          "com.figma.scopes": [
            "FONT_SIZE"
          ]
        }
      },
      "body-xs": {
        "$type": "number",
        "$value": 12,
        "$extensions": {
          "com.figma.variableId": "VariableID:5162:615",
          "com.figma.scopes": [
            "FONT_SIZE"
          ]
        }
      },
      "body-sm": {
        "$type": "number",
        "$value": 14,
        "$extensions": {
          "com.figma.variableId": "VariableID:5162:616",
          "com.figma.scopes": [
            "FONT_SIZE"
          ]
        }
      },
      "label-lg": {
        "$type": "number",
        "$value": 16,
        "$extensions": {
          "com.figma.variableId": "VariableID:5162:617",
          "com.figma.scopes": [
            "FONT_SIZE"
          ]
        }
      },
      "label-md": {
        "$type": "number",
        "$value": 14,
        "$extensions": {
          "com.figma.variableId": "VariableID:5162:612",
          "com.figma.scopes": [
            "FONT_SIZE"
          ]
        }
      },
      "label-sm": {
        "$type": "number",
        "$value": 12,
        "$extensions": {
          "com.figma.variableId": "VariableID:5162:611",
          "com.figma.scopes": [
            "FONT_SIZE"
          ]
        }
      },
      "label-xs": {
        "$type": "number",
        "$value": 10,
        "$extensions": {
          "com.figma.variableId": "VariableID:5324:2490",
          "com.figma.scopes": [
            "FONT_SIZE"
          ]
        }
      }
    },
    "Forbes Media": {
      "heading-lg": {
        "$type": "number",
        "$value": 32,
        "$extensions": {
          "com.figma.variableId": "VariableID:6028:2198",
          "com.figma.scopes": [
            "FONT_SIZE"
          ]
        }
      },
      "heading-md": {
        "$type": "number",
        "$value": 24,
        "$extensions": {
          "com.figma.variableId": "VariableID:6028:2199",
          "com.figma.scopes": [
            "FONT_SIZE"
          ]
        }
      },
      "heading-sm": {
        "$type": "number",
        "$value": 20,
        "$extensions": {
          "com.figma.variableId": "VariableID:6028:2200",
          "com.figma.scopes": [
            "FONT_SIZE"
          ]
        }
      },
      "heading-xs": {
        "$type": "number",
        "$value": 18,
        "$extensions": {
          "com.figma.variableId": "VariableID:6028:2224",
          "com.figma.scopes": [
            "FONT_SIZE"
          ]
        }
      },
      "body-lg-serif": {
        "$type": "number",
        "$value": 16,
        "$extensions": {
          "com.figma.variableId": "VariableID:6028:2225",
          "com.figma.scopes": [
            "FONT_SIZE"
          ]
        }
      },
      "body-lg": {
        "$type": "number",
        "$value": 18,
        "$extensions": {
          "com.figma.variableId": "VariableID:6028:2205",
          "com.figma.scopes": [
            "FONT_SIZE"
          ]
        }
      },
      "body-md": {
        "$type": "number",
        "$value": 16,
        "$extensions": {
          "com.figma.variableId": "VariableID:6028:2206",
          "com.figma.scopes": [
            "FONT_SIZE"
          ]
        }
      },
      "body-sm": {
        "$type": "number",
        "$value": 14,
        "$extensions": {
          "com.figma.variableId": "VariableID:6028:2208",
          "com.figma.scopes": [
            "FONT_SIZE"
          ]
        }
      },
      "body-xs": {
        "$type": "number",
        "$value": 12,
        "$extensions": {
          "com.figma.variableId": "VariableID:6028:2207",
          "com.figma.scopes": [
            "FONT_SIZE"
          ]
        }
      },
      "body-2xs": {
        "$type": "number",
        "$value": 10,
        "$extensions": {
          "com.figma.variableId": "VariableID:12942:212",
          "com.figma.scopes": [
            "FONT_SIZE"
          ]
        }
      },
      "label-eyebrow": {
        "$type": "number",
        "$value": 14,
        "$extensions": {
          "com.figma.variableId": "VariableID:6028:2209",
          "com.figma.scopes": [
            "FONT_SIZE"
          ]
        }
      },
      "label-breadcrumb": {
        "$type": "number",
        "$value": 10,
        "$extensions": {
          "com.figma.variableId": "VariableID:6028:2210",
          "com.figma.scopes": [
            "FONT_SIZE"
          ]
        }
      }
    }
  },
  "$extensions": {
    "com.figma.modeName": "Mobile"
  }
}